ice_age/__init__.py
ice_age-0.0.1.dist-info/LICENSE.txt
ice_age-0.0.1.dist-info/METADATA
ice_age-0.0.1.dist-info/WHEEL
ice_age-0.0.1.dist-info/top_level.txt
ice_age-0.0.1.dist-info/RECORD
