Metadata-Version: 2.1
Name: ice-age
Version: 0.0.1
Summary: freeze your ENVironment
Home-page: https://github.com/dpep/ice_age_py
Author: Daniel Pepper
License: MIT
Platform: any
Classifier: License :: OSI Approved :: MIT License
Classifier: Natural Language :: English
Classifier: Operating System :: OS Independent
Classifier: Topic :: Utilities
